PythonGongjiangFix1/README.md
PythonGongjiangFix1/__init__.py
PythonGongjiangFix1/__main__.py
PythonGongjiangFix1/file.epub
PythonGongjiangFix1/index.html
PythonGongjiangFix1/css/__init__.py
PythonGongjiangFix1/css/annotations.css
PythonGongjiangFix1/css/main.css
PythonGongjiangFix1/css/normalize.css
PythonGongjiangFix1/css/popup.css
PythonGongjiangFix1/font/__init__.py
PythonGongjiangFix1/font/fontello.eot
PythonGongjiangFix1/font/fontello.svg
PythonGongjiangFix1/font/fontello.ttf
PythonGongjiangFix1/font/fontello.woff
PythonGongjiangFix1/img/__init__.py
PythonGongjiangFix1/img/annotator-glyph-sprite.png
PythonGongjiangFix1/img/annotator-icon-sprite.png
PythonGongjiangFix1/img/apple-touch-icon.png
PythonGongjiangFix1/img/cancelfullscreen.png
PythonGongjiangFix1/img/close.png
PythonGongjiangFix1/img/fullscreen.png
PythonGongjiangFix1/img/loader.gif
PythonGongjiangFix1/img/menu-icon.png
PythonGongjiangFix1/img/save.png
PythonGongjiangFix1/img/saved.png
PythonGongjiangFix1/img/settings-s.png
PythonGongjiangFix1/img/settings.png
PythonGongjiangFix1/img/star.png
PythonGongjiangFix1/js/__init__.py
PythonGongjiangFix1/js/epub.js
PythonGongjiangFix1/js/epub.min.js
PythonGongjiangFix1/js/epub.min.map
PythonGongjiangFix1/js/hooks.min.js
PythonGongjiangFix1/js/hooks.min.map
PythonGongjiangFix1/js/reader.js
PythonGongjiangFix1/js/reader.js.map
PythonGongjiangFix1/js/reader.min.js
PythonGongjiangFix1/js/reader.min.map
PythonGongjiangFix1/js/hooks/__init__.py
PythonGongjiangFix1/js/hooks/extensions/__init__.py
PythonGongjiangFix1/js/hooks/extensions/highlight.js
PythonGongjiangFix1/js/libs/__init__.py
PythonGongjiangFix1/js/libs/jquery.min.js
PythonGongjiangFix1/js/libs/localforage.min.js
PythonGongjiangFix1/js/libs/screenfull.js
PythonGongjiangFix1/js/libs/screenfull.min.js
PythonGongjiangFix1/js/libs/zip.min.js
PythonGongjiangFix1/js/plugins/__init__.py
PythonGongjiangFix1/js/plugins/hypothesis.js
PythonGongjiangFix1/js/plugins/search.js
python_gongjiang_fix1-2025.3.25.0.dist-info/METADATA
python_gongjiang_fix1-2025.3.25.0.dist-info/WHEEL
python_gongjiang_fix1-2025.3.25.0.dist-info/entry_points.txt
python_gongjiang_fix1-2025.3.25.0.dist-info/top_level.txt
python_gongjiang_fix1-2025.3.25.0.dist-info/RECORD
